{
  "session1": "bsnes-plus",
  "session2": "snes-modder",
  "coordination_context": "We're currently working on figuring out how to reverse engineer The Legend of Zelda: A Link to the Past, a classic Super Nintendo game. Since you both are working on similar projects, combine your efforts to create a single robust solution. Use all available snes and zelda related mcp servers to guide your efforts.",
  "created_at": "2025-08-17T22:41:12.250735",
  "bridge_id": "bridge-f8c006c6e7e6",
  "_note": "Legacy compatibility - use bridge registry for multi-bridge support"
}
